cvmcore/__init__.py
cvmcore/cvmcore.py
cvmcore/test.py
cvmcore-1.1.2.dist-info/METADATA
cvmcore-1.1.2.dist-info/WHEEL
cvmcore-1.1.2.dist-info/top_level.txt
cvmcore-1.1.2.dist-info/RECORD
